gg/main.py
gracegit-0.1.2.dist-info/METADATA
gracegit-0.1.2.dist-info/WHEEL
gracegit-0.1.2.dist-info/entry_points.txt
gracegit-0.1.2.dist-info/top_level.txt
gracegit-0.1.2.dist-info/RECORD
