Metadata-Version: 2.4
Name: gracegit
Version: 0.1.2
Summary: A simple, crossplatform, CLI interface for simple Git actions
Project-URL: Homepage, https://github.com/gyoder/gracegit
Project-URL: Repository, https://github.com/gyoder/gracegit.git
Project-URL: Bug Tracker, https://github.com/gyoder/gracegit/issues
Requires-Python: >=3.10
Requires-Dist: gitpython>=3.1.44
Requires-Dist: typer>=0.16.0
